odoo/addons/ssi_related_attachment_mixin/README.rst
odoo/addons/ssi_related_attachment_mixin/__init__.py
odoo/addons/ssi_related_attachment_mixin/__manifest__.py
odoo/addons/ssi_related_attachment_mixin/menu.xml
odoo/addons/ssi_related_attachment_mixin/i18n/ssi_related_attachment_mixin.pot
odoo/addons/ssi_related_attachment_mixin/models/__init__.py
odoo/addons/ssi_related_attachment_mixin/models/attachment_related_attachment.py
odoo/addons/ssi_related_attachment_mixin/models/attachment_related_attachment_category.py
odoo/addons/ssi_related_attachment_mixin/models/attachment_related_attachment_detail.py
odoo/addons/ssi_related_attachment_mixin/models/attachment_related_attachment_template.py
odoo/addons/ssi_related_attachment_mixin/models/ir_model.py
odoo/addons/ssi_related_attachment_mixin/models/mixin_related_attachment.py
odoo/addons/ssi_related_attachment_mixin/security/ir.model.access.csv
odoo/addons/ssi_related_attachment_mixin/static/description/icon.png
odoo/addons/ssi_related_attachment_mixin/templates/related_attachment_templates.xml
odoo/addons/ssi_related_attachment_mixin/views/attachment_related_attachment.xml
odoo/addons/ssi_related_attachment_mixin/views/attachment_related_attachment_category_views.xml
odoo/addons/ssi_related_attachment_mixin/views/attachment_related_attachment_template_detail_views.xml
odoo/addons/ssi_related_attachment_mixin/views/attachment_related_attachment_template_views.xml
odoo/addons/ssi_related_attachment_mixin/views/ir_model_views.xml
odoo/addons/ssi_related_attachment_mixin/wizards/__init__.py
odoo/addons/ssi_related_attachment_mixin/wizards/attachment_related_attachment_import.py
odoo/addons/ssi_related_attachment_mixin/wizards/attachment_related_attachment_import.xml
odoo14_addon_ssi_related_attachment_mixin-14.0.2.10.1.dist-info/METADATA
odoo14_addon_ssi_related_attachment_mixin-14.0.2.10.1.dist-info/WHEEL
odoo14_addon_ssi_related_attachment_mixin-14.0.2.10.1.dist-info/top_level.txt
odoo14_addon_ssi_related_attachment_mixin-14.0.2.10.1.dist-info/RECORD
